{
  "updated": 1783083780.9397125,
  "count": 20,
  "alerts": [
    {
      "ticker": "SLBT",
      "type": "contract",
      "score": 82.19060576973963,
      "sector": "Biological Products, (No Diagnostic Substances)",
      "headline": "$8562M contract \u2014 BROOKHAVEN SCIENCE ASSOCIATES LLC",
      "why": "$8562M is the award's LIFETIME total to BROOKHAVEN SCIENCE ASSOCIATES LLC (Biological Products, (No Diagnostic Substances)) \u2014 USAspending lists award vehicles, not just fresh signings, so VERIFY recency before acting. (v2 will use SEC 8-K 'material agreement' filings for true fresh-deal catalysts.)",
      "details": {
        "amount": 8561512218.42,
        "agency": "Department of Energy",
        "action_date": "2015-01-05",
        "recipient": "BROOKHAVEN SCIENCE ASSOCIATES LLC",
        "matched_ticker": true,
        "cheapness": null
      },
      "link": "https://www.usaspending.gov/search",
      "created_at": 1783083758.8625417
    },
    {
      "ticker": "HON",
      "type": "contract",
      "score": 73.5,
      "sector": "Aircraft Engines & Engine Parts",
      "headline": "$17489M contract \u2014 HONEYWELL FEDERAL MANUFACTURING & TECHNO",
      "why": "$17489M is the award's LIFETIME total to HONEYWELL FEDERAL MANUFACTURING & TECHNO (Aircraft Engines & Engine Parts) \u2014 USAspending lists award vehicles, not just fresh signings, so VERIFY recency before acting. (v2 will use SEC 8-K 'material agreement' filings for true fresh-deal catalysts.)",
      "details": {
        "amount": 17488650862.28,
        "agency": "Department of Energy",
        "action_date": "2015-07-09",
        "recipient": "HONEYWELL FEDERAL MANUFACTURING & TECHNOLOGIES, LLC",
        "matched_ticker": true,
        "cheapness": 0.729
      },
      "link": "https://www.usaspending.gov/search",
      "created_at": 1783083756.9898605
    },
    {
      "ticker": "ACN",
      "type": "contract",
      "score": 69.0,
      "sector": "Services-Business Services, Nec",
      "headline": "$935M contract \u2014 ACCENTURE FEDERAL SERVICES LLC",
      "why": "$935M is the award's LIFETIME total to ACCENTURE FEDERAL SERVICES LLC (Services-Business Services, Nec) \u2014 USAspending lists award vehicles, not just fresh signings, so VERIFY recency before acting. (v2 will use SEC 8-K 'material agreement' filings for true fresh-deal catalysts.)",
      "details": {
        "amount": 934930527.41,
        "agency": "Department of Education",
        "action_date": "2019-02-20",
        "recipient": "ACCENTURE FEDERAL SERVICES LLC",
        "matched_ticker": true,
        "cheapness": 0.952
      },
      "link": "https://www.usaspending.gov/search",
      "created_at": 1783083772.1863997
    },
    {
      "ticker": "LMT",
      "type": "contract",
      "score": 66.3,
      "sector": "Guided Missiles & Space Vehicles & Parts",
      "headline": "$15556M contract \u2014 LOCKHEED MARTIN CORP",
      "why": "$15556M is the award's LIFETIME total to LOCKHEED MARTIN CORP (Guided Missiles & Space Vehicles & Parts) \u2014 USAspending lists award vehicles, not just fresh signings, so VERIFY recency before acting. (v2 will use SEC 8-K 'material agreement' filings for true fresh-deal catalysts.)",
      "details": {
        "amount": 15555973334.93,
        "agency": "National Aeronautics and Space Administration",
        "action_date": "2006-09-06",
        "recipient": "LOCKHEED MARTIN CORP",
        "matched_ticker": true,
        "cheapness": 0.56
      },
      "link": "https://www.usaspending.gov/search",
      "created_at": 1783083757.871754
    },
    {
      "ticker": "III",
      "type": "contract",
      "score": 66.0,
      "sector": "Services-Management Consulting Services",
      "headline": "$1586M contract \u2014 GENERAL DYNAMICS INFORMATION TECHNOLOGY,",
      "why": "$1586M is the award's LIFETIME total to GENERAL DYNAMICS INFORMATION TECHNOLOGY, (Services-Management Consulting Services) \u2014 USAspending lists award vehicles, not just fresh signings, so VERIFY recency before acting. (v2 will use SEC 8-K 'material agreement' filings for true fresh-deal catalysts.)",
      "details": {
        "amount": 1585600444.54,
        "agency": "Department of State",
        "action_date": "2019-06-19",
        "recipient": "GENERAL DYNAMICS INFORMATION TECHNOLOGY, INC.",
        "matched_ticker": true,
        "cheapness": 0.797
      },
      "link": "https://www.usaspending.gov/search",
      "created_at": 1783083767.0774207
    },
    {
      "ticker": "NOC",
      "type": "contract",
      "score": 65.5,
      "sector": "Search, Detection, Navigation, Guidance, Aeronautical Sys",
      "headline": "$4431M contract \u2014 NORTHROP GRUMMAN SYSTEMS CORPORATION",
      "why": "$4431M is the award's LIFETIME total to NORTHROP GRUMMAN SYSTEMS CORPORATION (Search, Detection, Navigation, Guidance, Aeronautical Sys) \u2014 USAspending lists award vehicles, not just fresh signings, so VERIFY recency before acting. (v2 will use SEC 8-K 'material agreement' filings for true fresh-deal catalysts.)",
      "details": {
        "amount": 4430784857.0,
        "agency": "National Aeronautics and Space Administration",
        "action_date": "2006-04-17",
        "recipient": "NORTHROP GRUMMAN SYSTEMS CORPORATION",
        "matched_ticker": true,
        "cheapness": 0.663
      },
      "link": "https://www.usaspending.gov/search",
      "created_at": 1783083760.3442748
    },
    {
      "ticker": "BAH",
      "type": "contract",
      "score": 64.5,
      "sector": "Services-Management Consulting Services",
      "headline": "$1168M contract \u2014 BOOZ ALLEN HAMILTON INC",
      "why": "$1168M is the award's LIFETIME total to BOOZ ALLEN HAMILTON INC (Services-Management Consulting Services) \u2014 USAspending lists award vehicles, not just fresh signings, so VERIFY recency before acting. (v2 will use SEC 8-K 'material agreement' filings for true fresh-deal catalysts.)",
      "details": {
        "amount": 1167667763.45,
        "agency": "General Services Administration",
        "action_date": "2022-09-06",
        "recipient": "BOOZ ALLEN HAMILTON INC",
        "matched_ticker": true,
        "cheapness": 0.796
      },
      "link": "https://www.usaspending.gov/search",
      "created_at": 1783083768.9407344
    },
    {
      "ticker": "AMTM",
      "type": "contract",
      "score": 63.2,
      "sector": "Services-Business Services, Nec",
      "headline": "$746M contract \u2014 AMENTUM SERVICES, INC.",
      "why": "$746M is the award's LIFETIME total to AMENTUM SERVICES, INC. (Services-Business Services, Nec) \u2014 USAspending lists award vehicles, not just fresh signings, so VERIFY recency before acting. (v2 will use SEC 8-K 'material agreement' filings for true fresh-deal catalysts.)",
      "details": {
        "amount": 745567173.77,
        "agency": "Department of Homeland Security",
        "action_date": "2021-07-01",
        "recipient": "AMENTUM SERVICES, INC.",
        "matched_ticker": true,
        "cheapness": 0.82
      },
      "link": "https://www.usaspending.gov/search",
      "created_at": 1783083777.8681524
    },
    {
      "ticker": "NOC",
      "type": "contract",
      "score": 61.1,
      "sector": "Search, Detection, Navigation, Guidance, Aeronautical Sys",
      "headline": "$1615M contract \u2014 NORTHROP GRUMMAN SYSTEMS CORPORATION",
      "why": "$1615M is the award's LIFETIME total to NORTHROP GRUMMAN SYSTEMS CORPORATION (Search, Detection, Navigation, Guidance, Aeronautical Sys) \u2014 USAspending lists award vehicles, not just fresh signings, so VERIFY recency before acting. (v2 will use SEC 8-K 'material agreement' filings for true fresh-deal catalysts.)",
      "details": {
        "amount": 1614792955.3,
        "agency": "National Aeronautics and Space Administration",
        "action_date": "2015-09-03",
        "recipient": "NORTHROP GRUMMAN SYSTEMS CORPORATION",
        "matched_ticker": true,
        "cheapness": 0.663
      },
      "link": "https://www.usaspending.gov/search",
      "created_at": 1783083765.1399004
    },
    {
      "ticker": "LDOS",
      "type": "contract",
      "score": 60.3,
      "sector": "Services-Computer Integrated Systems Design",
      "headline": "$1018M contract \u2014 LEIDOS, INC.",
      "why": "$1018M is the award's LIFETIME total to LEIDOS, INC. (Services-Computer Integrated Systems Design) \u2014 USAspending lists award vehicles, not just fresh signings, so VERIFY recency before acting. (v2 will use SEC 8-K 'material agreement' filings for true fresh-deal catalysts.)",
      "details": {
        "amount": 1018053974.0,
        "agency": "Department of Energy",
        "action_date": "2018-12-31",
        "recipient": "LEIDOS, INC.",
        "matched_ticker": true,
        "cheapness": 0.695
      },
      "link": "https://www.usaspending.gov/search",
      "created_at": 1783083770.7338
    },
    {
      "ticker": "LDOS",
      "type": "contract",
      "score": 59.8,
      "sector": "Services-Computer Integrated Systems Design",
      "headline": "$913M contract \u2014 LEIDOS, INC.",
      "why": "$913M is the award's LIFETIME total to LEIDOS, INC. (Services-Computer Integrated Systems Design) \u2014 USAspending lists award vehicles, not just fresh signings, so VERIFY recency before acting. (v2 will use SEC 8-K 'material agreement' filings for true fresh-deal catalysts.)",
      "details": {
        "amount": 912605172.5,
        "agency": "General Services Administration",
        "action_date": "2022-09-14",
        "recipient": "LEIDOS, INC.",
        "matched_ticker": true,
        "cheapness": 0.695
      },
      "link": "https://www.usaspending.gov/search",
      "created_at": 1783083772.186517
    },
    {
      "ticker": "ORCL",
      "type": "contract",
      "score": 54.1,
      "sector": "Services-Prepackaged Software",
      "headline": "$736M contract \u2014 ORACLE HEALTH GOVERNMENT SERVICES, INC.",
      "why": "$736M is the award's LIFETIME total to ORACLE HEALTH GOVERNMENT SERVICES, INC. (Services-Prepackaged Software) \u2014 USAspending lists award vehicles, not just fresh signings, so VERIFY recency before acting. (v2 will use SEC 8-K 'material agreement' filings for true fresh-deal catalysts.)",
      "details": {
        "amount": 735950421.88,
        "agency": "Department of Veterans Affairs",
        "action_date": "2022-05-01",
        "recipient": "ORACLE HEALTH GOVERNMENT SERVICES, INC.",
        "matched_ticker": true,
        "cheapness": 0.558
      },
      "link": "https://www.usaspending.gov/search",
      "created_at": 1783083779.5049639
    },
    {
      "ticker": "BA",
      "type": "contract",
      "score": 51.9,
      "sector": "Aircraft",
      "headline": "$22438M contract \u2014 THE BOEING COMPANY",
      "why": "$22438M is the award's LIFETIME total to THE BOEING COMPANY (Aircraft) \u2014 USAspending lists award vehicles, not just fresh signings, so VERIFY recency before acting. (v2 will use SEC 8-K 'material agreement' filings for true fresh-deal catalysts.)",
      "details": {
        "amount": 22437793940.54,
        "agency": "National Aeronautics and Space Administration",
        "action_date": "1993-11-15",
        "recipient": "THE BOEING COMPANY",
        "matched_ticker": true,
        "cheapness": 0.222
      },
      "link": "https://www.usaspending.gov/search",
      "created_at": 1783083755.7406516
    },
    {
      "ticker": "OWL",
      "type": "contract",
      "score": 51.5,
      "sector": "Investment Advice",
      "headline": "$1989M contract \u2014 BLUE ORIGIN MANUFACTURING, LLC",
      "why": "$1989M is the award's LIFETIME total to BLUE ORIGIN MANUFACTURING, LLC (Investment Advice) \u2014 USAspending lists award vehicles, not just fresh signings, so VERIFY recency before acting. (v2 will use SEC 8-K 'material agreement' filings for true fresh-deal catalysts.)",
      "details": {
        "amount": 1988511190.15,
        "agency": "National Aeronautics and Space Administration",
        "action_date": "2023-05-18",
        "recipient": "BLUE ORIGIN MANUFACTURING, LLC",
        "matched_ticker": true,
        "cheapness": 0.381
      },
      "link": "https://www.usaspending.gov/search",
      "created_at": 1783083765.139796
    },
    {
      "ticker": "CACI",
      "type": "contract",
      "score": 48.3,
      "sector": "Services-Computer Integrated Systems Design",
      "headline": "$792M contract \u2014 CACI, INC. - FEDERAL",
      "why": "$792M is the award's LIFETIME total to CACI, INC. - FEDERAL (Services-Computer Integrated Systems Design) \u2014 USAspending lists award vehicles, not just fresh signings, so VERIFY recency before acting. (v2 will use SEC 8-K 'material agreement' filings for true fresh-deal catalysts.)",
      "details": {
        "amount": 791865250.9,
        "agency": "General Services Administration",
        "action_date": "2024-05-01",
        "recipient": "CACI, INC. - FEDERAL",
        "matched_ticker": true,
        "cheapness": 0.383
      },
      "link": "https://www.usaspending.gov/search",
      "created_at": 1783083774.0167809
    },
    {
      "ticker": "BA",
      "type": "contract",
      "score": 46.4,
      "sector": "Aircraft",
      "headline": "$2593M contract \u2014 THE BOEING COMPANY",
      "why": "$2593M is the award's LIFETIME total to THE BOEING COMPANY (Aircraft) \u2014 USAspending lists award vehicles, not just fresh signings, so VERIFY recency before acting. (v2 will use SEC 8-K 'material agreement' filings for true fresh-deal catalysts.)",
      "details": {
        "amount": 2593215439.0,
        "agency": "National Aeronautics and Space Administration",
        "action_date": "2019-10-16",
        "recipient": "THE BOEING COMPANY",
        "matched_ticker": true,
        "cheapness": 0.222
      },
      "link": "https://www.usaspending.gov/search",
      "created_at": 1783083761.2967694
    },
    {
      "ticker": "BA",
      "type": "contract",
      "score": 44.2,
      "sector": "Aircraft",
      "headline": "$1288M contract \u2014 THE BOEING COMPANY",
      "why": "$1288M is the award's LIFETIME total to THE BOEING COMPANY (Aircraft) \u2014 USAspending lists award vehicles, not just fresh signings, so VERIFY recency before acting. (v2 will use SEC 8-K 'material agreement' filings for true fresh-deal catalysts.)",
      "details": {
        "amount": 1287720376.0,
        "agency": "National Aeronautics and Space Administration",
        "action_date": "2012-10-01",
        "recipient": "THE BOEING COMPANY",
        "matched_ticker": true,
        "cheapness": 0.222
      },
      "link": "https://www.usaspending.gov/search",
      "created_at": 1783083767.0775406
    },
    {
      "ticker": "LRCX",
      "type": "contract",
      "score": 42.5,
      "sector": "Special Industry Machinery, Nec",
      "headline": "$2518M contract \u2014 ASSOCIATION OF UNIVERSITIES FOR RESEARCH",
      "why": "$2518M is the award's LIFETIME total to ASSOCIATION OF UNIVERSITIES FOR RESEARCH (Special Industry Machinery, Nec) \u2014 USAspending lists award vehicles, not just fresh signings, so VERIFY recency before acting. (v2 will use SEC 8-K 'material agreement' filings for true fresh-deal catalysts.)",
      "details": {
        "amount": 2517978040.0,
        "agency": "National Aeronautics and Space Administration",
        "action_date": "1987-09-15",
        "recipient": "ASSOCIATION OF UNIVERSITIES FOR RESEARCH IN ASTRONOMY, INC.",
        "matched_ticker": true,
        "cheapness": 0.12
      },
      "link": "https://www.usaspending.gov/search",
      "created_at": 1783083763.2206974
    },
    {
      "ticker": "ROAD",
      "type": "contract",
      "score": 40.4,
      "sector": "Heavy Construction Other Than Bldg Const - Contractors",
      "headline": "$760M contract \u2014 HENSEL PHELPS CONSTRUCTION CO",
      "why": "$760M is the award's LIFETIME total to HENSEL PHELPS CONSTRUCTION CO (Heavy Construction Other Than Bldg Const - Contractors) \u2014 USAspending lists award vehicles, not just fresh signings, so VERIFY recency before acting. (v2 will use SEC 8-K 'material agreement' filings for true fresh-deal catalysts.)",
      "details": {
        "amount": 760083862.0,
        "agency": "Department of Health and Human Services",
        "action_date": "2022-03-22",
        "recipient": "HENSEL PHELPS CONSTRUCTION CO",
        "matched_ticker": true,
        "cheapness": 0.16
      },
      "link": "https://www.usaspending.gov/search",
      "created_at": 1783083775.9912415
    },
    {
      "ticker": "SPCX",
      "type": "contract",
      "score": 38.4,
      "sector": "Services-Computer Programming, Data Processing, Etc.",
      "headline": "$3048M contract \u2014 SPACE EXPLORATION TECHNOLOGIES CORP.",
      "why": "$3048M is the award's LIFETIME total to SPACE EXPLORATION TECHNOLOGIES CORP. (Services-Computer Programming, Data Processing, Etc.) \u2014 USAspending lists award vehicles, not just fresh signings, so VERIFY recency before acting. (v2 will use SEC 8-K 'material agreement' filings for true fresh-deal catalysts.)",
      "details": {
        "amount": 3047851482.99,
        "agency": "National Aeronautics and Space Administration",
        "action_date": "2020-05-13",
        "recipient": "SPACE EXPLORATION TECHNOLOGIES CORP.",
        "matched_ticker": true,
        "cheapness": 0.0
      },
      "link": "https://www.usaspending.gov/search",
      "created_at": 1783083761.2966635
    }
  ]
}