{
  "updated": 1784309780.0183163,
  "count": 31,
  "alerts": [
    {
      "ticker": "N/A",
      "type": "insider_cluster",
      "score": 100.0,
      "sector": "Unknown",
      "headline": "5 insiders bought N/A ($78.8M)",
      "why": "5 insiders put personal cash into N/A (Unknown). Clustered open-market buys are the strongest documented edge \u2014 insiders sell for many reasons but buy for only one.",
      "details": {
        "insiders": 5,
        "total_value": 78783782,
        "owners": "Nagpal Ankur,Manulife (International) Ltd,Manulife (Singapore) Pte. Ltd.,Manufacturers Life Insurance Co (Bermuda Branch),Manufacturers Life Reinsurance Ltd",
        "issuer": "USVC Venture Capital Access Fund",
        "officer": true,
        "cheapness": null
      },
      "link": "https://www.sec.gov/cgi-bin/browse-edgar?action=getcompany&company=N/A&type=4&owner=only&output=atom",
      "created_at": 1784309727.4770782
    },
    {
      "ticker": "NONE",
      "type": "insider_cluster",
      "score": 100.0,
      "sector": "Unknown",
      "headline": "5 insiders bought NONE ($0.0M)",
      "why": "5 insiders put personal cash into NONE (Unknown). Clustered open-market buys are the strongest documented edge \u2014 insiders sell for many reasons but buy for only one.",
      "details": {
        "insiders": 5,
        "total_value": 1822,
        "owners": "Monte Mark David,Starr Gayle P,Jenkins Brandon T.,Miller Benjamin S.,Staloch Alison",
        "issuer": "Fundrise Real Estate Interval Fund, LLC",
        "officer": true,
        "cheapness": null
      },
      "link": "https://www.sec.gov/cgi-bin/browse-edgar?action=getcompany&company=NONE&type=4&owner=only&output=atom",
      "created_at": 1784309737.4855306
    },
    {
      "ticker": "III",
      "type": "contract",
      "score": 61.4,
      "sector": "Services-Management Consulting Services",
      "headline": "$578M contract \u2014 GENERAL DYNAMICS INFORMATION TECHNOLOGY,",
      "why": "$578M is the award's LIFETIME total to GENERAL DYNAMICS INFORMATION TECHNOLOGY, (Services-Management Consulting Services) \u2014 USAspending lists award vehicles, not just fresh signings, so VERIFY recency before acting. (v2 will use SEC 8-K 'material agreement' filings for true fresh-deal catalysts.)",
      "details": {
        "amount": 578333381.99,
        "agency": "General Services Administration",
        "action_date": "2020-11-01",
        "recipient": "GENERAL DYNAMICS INFORMATION TECHNOLOGY, INC.",
        "matched_ticker": true,
        "cheapness": 0.801
      },
      "link": "https://www.usaspending.gov/search",
      "created_at": 1784309744.360932
    },
    {
      "ticker": "LDOS",
      "type": "contract",
      "score": 60.9,
      "sector": "Services-Computer Integrated Systems Design",
      "headline": "$862M contract \u2014 LEIDOS, INC.",
      "why": "$862M is the award's LIFETIME total to LEIDOS, INC. (Services-Computer Integrated Systems Design) \u2014 USAspending lists award vehicles, not just fresh signings, so VERIFY recency before acting. (v2 will use SEC 8-K 'material agreement' filings for true fresh-deal catalysts.)",
      "details": {
        "amount": 862390010.14,
        "agency": "Department of Homeland Security",
        "action_date": "2019-10-01",
        "recipient": "LEIDOS, INC.",
        "matched_ticker": true,
        "cheapness": 0.735
      },
      "link": "https://www.usaspending.gov/search",
      "created_at": 1784309742.2397404
    },
    {
      "ticker": "GECC",
      "type": "contract",
      "score": 60.9,
      "sector": "Unknown",
      "headline": "$143M contract \u2014 GREAT HILL SOLUTIONS, LLC",
      "why": "$143M is the award's LIFETIME total to GREAT HILL SOLUTIONS, LLC (Unknown) \u2014 USAspending lists award vehicles, not just fresh signings, so VERIFY recency before acting. (v2 will use SEC 8-K 'material agreement' filings for true fresh-deal catalysts.)",
      "details": {
        "amount": 143045871.28,
        "agency": "Department of State",
        "action_date": "2021-12-15",
        "recipient": "GREAT HILL SOLUTIONS, LLC",
        "matched_ticker": true,
        "cheapness": 1.0
      },
      "link": "https://www.usaspending.gov/search",
      "created_at": 1784309757.095871
    },
    {
      "ticker": "ACN",
      "type": "contract",
      "score": 58.8,
      "sector": "Services-Business Services, Nec",
      "headline": "$146M contract \u2014 ACCENTURE FEDERAL SERVICES LLC",
      "why": "$146M is the award's LIFETIME total to ACCENTURE FEDERAL SERVICES LLC (Services-Business Services, Nec) \u2014 USAspending lists award vehicles, not just fresh signings, so VERIFY recency before acting. (v2 will use SEC 8-K 'material agreement' filings for true fresh-deal catalysts.)",
      "details": {
        "amount": 145900688.14,
        "agency": "Department of the Treasury",
        "action_date": "2025-08-15",
        "recipient": "ACCENTURE FEDERAL SERVICES LLC",
        "matched_ticker": true,
        "cheapness": 0.928
      },
      "link": "https://www.usaspending.gov/search",
      "created_at": 1784309755.0451035
    },
    {
      "ticker": "ORCL",
      "type": "contract",
      "score": 57.6,
      "sector": "Services-Prepackaged Software",
      "headline": "$1511M contract \u2014 ORACLE HEALTH GOVERNMENT SERVICES, INC.",
      "why": "$1511M is the award's LIFETIME total to ORACLE HEALTH GOVERNMENT SERVICES, INC. (Services-Prepackaged Software) \u2014 USAspending lists award vehicles, not just fresh signings, so VERIFY recency before acting. (v2 will use SEC 8-K 'material agreement' filings for true fresh-deal catalysts.)",
      "details": {
        "amount": 1511268663.21,
        "agency": "Department of Veterans Affairs",
        "action_date": "2018-05-17",
        "recipient": "ORACLE HEALTH GOVERNMENT SERVICES, INC.",
        "matched_ticker": true,
        "cheapness": 0.576
      },
      "link": "https://www.usaspending.gov/search",
      "created_at": 1784309739.9053557
    },
    {
      "ticker": "MMS",
      "type": "contract",
      "score": 57.1,
      "sector": "Services-Business Services, Nec",
      "headline": "$92M contract \u2014 MAXIMUS FEDERAL SERVICES, INC.",
      "why": "$92M is the award's LIFETIME total to MAXIMUS FEDERAL SERVICES, INC. (Services-Business Services, Nec) \u2014 USAspending lists award vehicles, not just fresh signings, so VERIFY recency before acting. (v2 will use SEC 8-K 'material agreement' filings for true fresh-deal catalysts.)",
      "details": {
        "amount": 92272612.3,
        "agency": "Department of the Treasury",
        "action_date": "2024-05-23",
        "recipient": "MAXIMUS FEDERAL SERVICES, INC.",
        "matched_ticker": true,
        "cheapness": 0.951
      },
      "link": "https://www.usaspending.gov/search",
      "created_at": 1784309765.6144078
    },
    {
      "ticker": "III",
      "type": "contract",
      "score": 56.9,
      "sector": "Services-Management Consulting Services",
      "headline": "$223M contract \u2014 GENERAL DYNAMICS INFORMATION TECHNOLOGY,",
      "why": "$223M is the award's LIFETIME total to GENERAL DYNAMICS INFORMATION TECHNOLOGY, (Services-Management Consulting Services) \u2014 USAspending lists award vehicles, not just fresh signings, so VERIFY recency before acting. (v2 will use SEC 8-K 'material agreement' filings for true fresh-deal catalysts.)",
      "details": {
        "amount": 223040341.3,
        "agency": "General Services Administration",
        "action_date": "2022-07-29",
        "recipient": "GENERAL DYNAMICS INFORMATION TECHNOLOGY, INC.",
        "matched_ticker": true,
        "cheapness": 0.801
      },
      "link": "https://www.usaspending.gov/search",
      "created_at": 1784309746.9579422
    },
    {
      "ticker": "III",
      "type": "contract",
      "score": 55.9,
      "sector": "Services-Management Consulting Services",
      "headline": "$180M contract \u2014 GENERAL DYNAMICS INFORMATION TECHNOLOGY,",
      "why": "$180M is the award's LIFETIME total to GENERAL DYNAMICS INFORMATION TECHNOLOGY, (Services-Management Consulting Services) \u2014 USAspending lists award vehicles, not just fresh signings, so VERIFY recency before acting. (v2 will use SEC 8-K 'material agreement' filings for true fresh-deal catalysts.)",
      "details": {
        "amount": 180222000.0,
        "agency": "General Services Administration",
        "action_date": "2025-06-30",
        "recipient": "GENERAL DYNAMICS INFORMATION TECHNOLOGY, INC.",
        "matched_ticker": true,
        "cheapness": 0.801
      },
      "link": "https://www.usaspending.gov/search",
      "created_at": 1784309751.414712
    },
    {
      "ticker": "SRCE",
      "type": "contract",
      "score": 53.3,
      "sector": "State Commercial Banks",
      "headline": "$70M contract \u2014 LOYAL SOURCE GOVERNMENT SERVICES LLC",
      "why": "$70M is the award's LIFETIME total to LOYAL SOURCE GOVERNMENT SERVICES LLC (State Commercial Banks) \u2014 USAspending lists award vehicles, not just fresh signings, so VERIFY recency before acting. (v2 will use SEC 8-K 'material agreement' filings for true fresh-deal catalysts.)",
      "details": {
        "amount": 70125954.61,
        "agency": "Department of Homeland Security",
        "action_date": "2025-09-28",
        "recipient": "LOYAL SOURCE GOVERNMENT SERVICES LLC",
        "matched_ticker": true,
        "cheapness": 0.865
      },
      "link": "https://www.usaspending.gov/search",
      "created_at": 1784309776.0697465
    },
    {
      "ticker": "ATLO",
      "type": "contract",
      "score": 52.6,
      "sector": "National Commercial Banks",
      "headline": "$115M contract \u2014 AMES FEDERAL CONTRACTING GROUP LLC",
      "why": "$115M is the award's LIFETIME total to AMES FEDERAL CONTRACTING GROUP LLC (National Commercial Banks) \u2014 USAspending lists award vehicles, not just fresh signings, so VERIFY recency before acting. (v2 will use SEC 8-K 'material agreement' filings for true fresh-deal catalysts.)",
      "details": {
        "amount": 115012088.09,
        "agency": "Department of the Interior",
        "action_date": "2025-03-21",
        "recipient": "AMES FEDERAL CONTRACTING GROUP LLC",
        "matched_ticker": true,
        "cheapness": 0.76
      },
      "link": "https://www.usaspending.gov/search",
      "created_at": 1784309759.150893
    },
    {
      "ticker": "LDOS",
      "type": "contract",
      "score": 50.8,
      "sector": "Services-Computer Integrated Systems Design",
      "headline": "$93M contract \u2014 LEIDOS, INC.",
      "why": "$93M is the award's LIFETIME total to LEIDOS, INC. (Services-Computer Integrated Systems Design) \u2014 USAspending lists award vehicles, not just fresh signings, so VERIFY recency before acting. (v2 will use SEC 8-K 'material agreement' filings for true fresh-deal catalysts.)",
      "details": {
        "amount": 92839252.78,
        "agency": "Federal Trade Commission",
        "action_date": "2020-11-30",
        "recipient": "LEIDOS, INC.",
        "matched_ticker": true,
        "cheapness": 0.735
      },
      "link": "https://www.usaspending.gov/search",
      "created_at": 1784309762.816508
    },
    {
      "ticker": "LMT",
      "type": "contract",
      "score": 50.2,
      "sector": "Guided Missiles & Space Vehicles & Parts",
      "headline": "$220M contract \u2014 LOCKHEED MARTIN CORPORATION",
      "why": "$220M is the award's LIFETIME total to LOCKHEED MARTIN CORPORATION (Guided Missiles & Space Vehicles & Parts) \u2014 USAspending lists award vehicles, not just fresh signings, so VERIFY recency before acting. (v2 will use SEC 8-K 'material agreement' filings for true fresh-deal catalysts.)",
      "details": {
        "amount": 220462628.03,
        "agency": "National Aeronautics and Space Administration",
        "action_date": "2021-04-26",
        "recipient": "LOCKHEED MARTIN CORPORATION",
        "matched_ticker": true,
        "cheapness": 0.591
      },
      "link": "https://www.usaspending.gov/search",
      "created_at": 1784309749.0827157
    },
    {
      "ticker": "NOC",
      "type": "contract",
      "score": 48.7,
      "sector": "Search, Detection, Navigation, Guidance, Aeronautical Sys",
      "headline": "$81M contract \u2014 NORTHROP GRUMMAN SYSTEMS CORPORATION",
      "why": "$81M is the award's LIFETIME total to NORTHROP GRUMMAN SYSTEMS CORPORATION (Search, Detection, Navigation, Guidance, Aeronautical Sys) \u2014 USAspending lists award vehicles, not just fresh signings, so VERIFY recency before acting. (v2 will use SEC 8-K 'material agreement' filings for true fresh-deal catalysts.)",
      "details": {
        "amount": 80635452.0,
        "agency": "National Aeronautics and Space Administration",
        "action_date": "2021-03-04",
        "recipient": "NORTHROP GRUMMAN SYSTEMS CORPORATION",
        "matched_ticker": true,
        "cheapness": 0.682
      },
      "link": "https://www.usaspending.gov/search",
      "created_at": 1784309771.6857395
    },
    {
      "ticker": "LHX",
      "type": "contract",
      "score": 45.0,
      "sector": "Search, Detection, Navigation, Guidance, Aeronautical Sys",
      "headline": "$71M contract \u2014 L3HARRIS TECHNOLOGIES, INC.",
      "why": "$71M is the award's LIFETIME total to L3HARRIS TECHNOLOGIES, INC. (Search, Detection, Navigation, Guidance, Aeronautical Sys) \u2014 USAspending lists award vehicles, not just fresh signings, so VERIFY recency before acting. (v2 will use SEC 8-K 'material agreement' filings for true fresh-deal catalysts.)",
      "details": {
        "amount": 70691799.0,
        "agency": "Department of Transportation",
        "action_date": "2026-03-31",
        "recipient": "L3HARRIS TECHNOLOGIES, INC.",
        "matched_ticker": true,
        "cheapness": 0.573
      },
      "link": "https://www.usaspending.gov/search",
      "created_at": 1784309774.0411022
    },
    {
      "ticker": "EOG",
      "type": "contract",
      "score": 43.7,
      "sector": "Crude Petroleum & Natural Gas",
      "headline": "$66M contract \u2014 EARTH RESOURCES TECHNOLOGY, LLC",
      "why": "$66M is the award's LIFETIME total to EARTH RESOURCES TECHNOLOGY, LLC (Crude Petroleum & Natural Gas) \u2014 USAspending lists award vehicles, not just fresh signings, so VERIFY recency before acting. (v2 will use SEC 8-K 'material agreement' filings for true fresh-deal catalysts.)",
      "details": {
        "amount": 66114894.99,
        "agency": "Department of Commerce",
        "action_date": "2021-03-29",
        "recipient": "EARTH RESOURCES TECHNOLOGY, LLC",
        "matched_ticker": true,
        "cheapness": 0.539
      },
      "link": "https://www.usaspending.gov/search",
      "created_at": 1784309778.2114544
    },
    {
      "ticker": "FCN",
      "type": "contract",
      "score": 42.2,
      "sector": "Services-Management Consulting Services",
      "headline": "$200M contract \u2014 LMI CONSULTING, LLC",
      "why": "$200M is the award's LIFETIME total to LMI CONSULTING, LLC (Services-Management Consulting Services) \u2014 USAspending lists award vehicles, not just fresh signings, so VERIFY recency before acting. (v2 will use SEC 8-K 'material agreement' filings for true fresh-deal catalysts.)",
      "details": {
        "amount": 200000000.0,
        "agency": "Department of Homeland Security",
        "action_date": "2026-05-20",
        "recipient": "LMI CONSULTING, LLC",
        "matched_ticker": true,
        "cheapness": 0.347
      },
      "link": "https://www.usaspending.gov/search",
      "created_at": 1784309751.414581
    },
    {
      "ticker": "WYY",
      "type": "contract",
      "score": 42.1,
      "sector": "Services-Computer Integrated Systems Design",
      "headline": "$96M contract \u2014 WIDEPOINT INTEGRATED SOLUTIONS CORP",
      "why": "$96M is the award's LIFETIME total to WIDEPOINT INTEGRATED SOLUTIONS CORP (Services-Computer Integrated Systems Design) \u2014 USAspending lists award vehicles, not just fresh signings, so VERIFY recency before acting. (v2 will use SEC 8-K 'material agreement' filings for true fresh-deal catalysts.)",
      "details": {
        "amount": 96236965.87,
        "agency": "Department of Homeland Security",
        "action_date": "2021-03-16",
        "recipient": "WIDEPOINT INTEGRATED SOLUTIONS CORP",
        "matched_ticker": true,
        "cheapness": 0.432
      },
      "link": "https://www.usaspending.gov/search",
      "created_at": 1784309762.8163676
    },
    {
      "ticker": "UMH",
      "type": "insider_cluster",
      "score": 41.8,
      "sector": "Real Estate Investment Trusts",
      "headline": "2 insiders bought UMH ($0.0M)",
      "why": "2 insiders put personal cash into UMH (Real Estate Investment Trusts). Clustered open-market buys are the strongest documented edge \u2014 insiders sell for many reasons but buy for only one. Valuation gate: rich (0.16).",
      "details": {
        "insiders": 2,
        "total_value": 2000,
        "owners": "Mitchell William Edward,Miller Kevin S.",
        "issuer": "UMH PROPERTIES, INC.",
        "officer": true,
        "cheapness": 0.161
      },
      "link": "https://www.sec.gov/cgi-bin/browse-edgar?action=getcompany&company=UMH&type=4&owner=only&output=atom",
      "created_at": 1784309736.7745478
    },
    {
      "ticker": "FCN",
      "type": "contract",
      "score": 39.7,
      "sector": "Services-Management Consulting Services",
      "headline": "$99M contract \u2014 DELOITTE CONSULTING LLP",
      "why": "$99M is the award's LIFETIME total to DELOITTE CONSULTING LLP (Services-Management Consulting Services) \u2014 USAspending lists award vehicles, not just fresh signings, so VERIFY recency before acting. (v2 will use SEC 8-K 'material agreement' filings for true fresh-deal catalysts.)",
      "details": {
        "amount": 99440632.77,
        "agency": "Department of Agriculture",
        "action_date": "2022-06-01",
        "recipient": "DELOITTE CONSULTING LLP",
        "matched_ticker": true,
        "cheapness": 0.347
      },
      "link": "https://www.usaspending.gov/search",
      "created_at": 1784309759.151001
    },
    {
      "ticker": "NTSK",
      "type": "insider_cluster",
      "score": 38.4,
      "sector": "Services-Prepackaged Software",
      "headline": "2 insiders bought NTSK ($14.4M)",
      "why": "2 insiders put personal cash into NTSK (Services-Prepackaged Software). Clustered open-market buys are the strongest documented edge \u2014 insiders sell for many reasons but buy for only one. Valuation gate: rich (0.24).",
      "details": {
        "insiders": 2,
        "total_value": 14432130,
        "owners": "ICONIQ Strategic Partners VIII Holdings, L.P.,Griffith William J.G.",
        "issuer": "Netskope Inc",
        "officer": false,
        "cheapness": 0.24
      },
      "link": "https://www.sec.gov/cgi-bin/browse-edgar?action=getcompany&company=NTSK&type=4&owner=only&output=atom",
      "created_at": 1784309729.619002
    },
    {
      "ticker": "EPSN",
      "type": "contract",
      "score": 38.2,
      "sector": "Crude Petroleum & Natural Gas",
      "headline": "$83M contract \u2014 EPSILON INC",
      "why": "$83M is the award's LIFETIME total to EPSILON INC (Crude Petroleum & Natural Gas) \u2014 USAspending lists award vehicles, not just fresh signings, so VERIFY recency before acting. (v2 will use SEC 8-K 'material agreement' filings for true fresh-deal catalysts.)",
      "details": {
        "amount": 83416921.71,
        "agency": "Department of Agriculture",
        "action_date": "2022-10-01",
        "recipient": "EPSILON INC",
        "matched_ticker": true,
        "cheapness": 0.317
      },
      "link": "https://www.usaspending.gov/search",
      "created_at": 1784309770.3739727
    },
    {
      "ticker": "ROAD",
      "type": "contract",
      "score": 37.8,
      "sector": "Heavy Construction Other Than Bldg Const - Contractors",
      "headline": "$329M contract \u2014 CADDELL CONSTRUCTION CO. (DE), LLC",
      "why": "$329M is the award's LIFETIME total to CADDELL CONSTRUCTION CO. (DE), LLC (Heavy Construction Other Than Bldg Const - Contractors) \u2014 USAspending lists award vehicles, not just fresh signings, so VERIFY recency before acting. (v2 will use SEC 8-K 'material agreement' filings for true fresh-deal catalysts.)",
      "details": {
        "amount": 328631437.0,
        "agency": "Department of State",
        "action_date": "2024-09-30",
        "recipient": "CADDELL CONSTRUCTION CO. (DE), LLC",
        "matched_ticker": true,
        "cheapness": 0.16
      },
      "link": "https://www.usaspending.gov/search",
      "created_at": 1784309746.9577584
    },
    {
      "ticker": "ROAD",
      "type": "contract",
      "score": 36.7,
      "sector": "Heavy Construction Other Than Bldg Const - Contractors",
      "headline": "$228M contract \u2014 CADDELL CONSTRUCTION CO. (DE), LLC",
      "why": "$228M is the award's LIFETIME total to CADDELL CONSTRUCTION CO. (DE), LLC (Heavy Construction Other Than Bldg Const - Contractors) \u2014 USAspending lists award vehicles, not just fresh signings, so VERIFY recency before acting. (v2 will use SEC 8-K 'material agreement' filings for true fresh-deal catalysts.)",
      "details": {
        "amount": 228009133.02,
        "agency": "Department of State",
        "action_date": "2018-12-28",
        "recipient": "CADDELL CONSTRUCTION CO. (DE), LLC",
        "matched_ticker": true,
        "cheapness": 0.16
      },
      "link": "https://www.usaspending.gov/search",
      "created_at": 1784309746.9578793
    },
    {
      "ticker": "GFL",
      "type": "contract",
      "score": 36.6,
      "sector": "Refuse Systems",
      "headline": "$86M contract \u2014 SIERRA TAHOE ENVIRONMENTAL MANAGEMENT, L",
      "why": "$86M is the award's LIFETIME total to SIERRA TAHOE ENVIRONMENTAL MANAGEMENT, L (Refuse Systems) \u2014 USAspending lists award vehicles, not just fresh signings, so VERIFY recency before acting. (v2 will use SEC 8-K 'material agreement' filings for true fresh-deal catalysts.)",
      "details": {
        "amount": 85826031.96,
        "agency": "Department of Agriculture",
        "action_date": "2023-12-31",
        "recipient": "SIERRA TAHOE ENVIRONMENTAL MANAGEMENT, LLC",
        "matched_ticker": true,
        "cheapness": 0.256
      },
      "link": "https://www.usaspending.gov/search",
      "created_at": 1784309768.3526688
    },
    {
      "ticker": "IPX",
      "type": "insider_cluster",
      "score": 36.0,
      "sector": "Miscellaneous Metal Ores",
      "headline": "2 insiders bought IPX ($2.4M)",
      "why": "2 insiders put personal cash into IPX (Miscellaneous Metal Ores). Clustered open-market buys are the strongest documented edge \u2014 insiders sell for many reasons but buy for only one. Valuation gate: rich (0.00).",
      "details": {
        "insiders": 2,
        "total_value": 2378393,
        "owners": "Arima Anastasios,Hannigan Todd",
        "issuer": "IPERIONX Ltd",
        "officer": true,
        "cheapness": 0.0
      },
      "link": "https://www.sec.gov/cgi-bin/browse-edgar?action=getcompany&company=IPX&type=4&owner=only&output=atom",
      "created_at": 1784309731.775993
    },
    {
      "ticker": "RDGL",
      "type": "insider_cluster",
      "score": 36.0,
      "sector": "Surgical & Medical Instruments & Apparatus",
      "headline": "2 insiders bought RDGL ($0.0M)",
      "why": "2 insiders put personal cash into RDGL (Surgical & Medical Instruments & Apparatus). Clustered open-market buys are the strongest documented edge \u2014 insiders sell for many reasons but buy for only one. Valuation gate: rich (0.00).",
      "details": {
        "insiders": 2,
        "total_value": 16220,
        "owners": "Weeks Brad Allan,Korenko Michael K",
        "issuer": "VIVOS INC",
        "officer": true,
        "cheapness": 0.0
      },
      "link": "https://www.sec.gov/cgi-bin/browse-edgar?action=getcompany&company=RDGL&type=4&owner=only&output=atom",
      "created_at": 1784309733.6192806
    },
    {
      "ticker": "LRCX",
      "type": "contract",
      "score": 35.4,
      "sector": "Special Industry Machinery, Nec",
      "headline": "$179M contract \u2014 ASSOCIATION OF UNIVERSITIES FOR RESEARCH",
      "why": "$179M is the award's LIFETIME total to ASSOCIATION OF UNIVERSITIES FOR RESEARCH (Special Industry Machinery, Nec) \u2014 USAspending lists award vehicles, not just fresh signings, so VERIFY recency before acting. (v2 will use SEC 8-K 'material agreement' filings for true fresh-deal catalysts.)",
      "details": {
        "amount": 178975557.0,
        "agency": "National Aeronautics and Space Administration",
        "action_date": "2019-07-01",
        "recipient": "ASSOCIATION OF UNIVERSITIES FOR RESEARCH IN ASTRONOMY, INC.",
        "matched_ticker": true,
        "cheapness": 0.142
      },
      "link": "https://www.usaspending.gov/search",
      "created_at": 1784309753.739689
    },
    {
      "ticker": "LRCX",
      "type": "contract",
      "score": 35.0,
      "sector": "Special Industry Machinery, Nec",
      "headline": "$155M contract \u2014 RESEARCH TRIANGLE INSTITUTE",
      "why": "$155M is the award's LIFETIME total to RESEARCH TRIANGLE INSTITUTE (Special Industry Machinery, Nec) \u2014 USAspending lists award vehicles, not just fresh signings, so VERIFY recency before acting. (v2 will use SEC 8-K 'material agreement' filings for true fresh-deal catalysts.)",
      "details": {
        "amount": 155224206.94,
        "agency": "Department of Health and Human Services",
        "action_date": "2019-09-25",
        "recipient": "RESEARCH TRIANGLE INSTITUTE",
        "matched_ticker": true,
        "cheapness": 0.142
      },
      "link": "https://www.usaspending.gov/search",
      "created_at": 1784309753.739789
    },
    {
      "ticker": "ROAD",
      "type": "contract",
      "score": 33.0,
      "sector": "Heavy Construction Other Than Bldg Const - Contractors",
      "headline": "$67M contract \u2014 MANSON CONSTRUCTION CO",
      "why": "$67M is the award's LIFETIME total to MANSON CONSTRUCTION CO (Heavy Construction Other Than Bldg Const - Contractors) \u2014 USAspending lists award vehicles, not just fresh signings, so VERIFY recency before acting. (v2 will use SEC 8-K 'material agreement' filings for true fresh-deal catalysts.)",
      "details": {
        "amount": 66917591.72,
        "agency": "Department of Commerce",
        "action_date": "2023-10-18",
        "recipient": "MANSON CONSTRUCTION CO",
        "matched_ticker": true,
        "cheapness": 0.16
      },
      "link": "https://www.usaspending.gov/search",
      "created_at": 1784309776.0698738
    }
  ]
}