{
  "updated": 1782168384.9676838,
  "count": 23,
  "valuations": {
    "BZFD": {
      "ticker": "BZFD",
      "computed_at": 1782168341.9980288,
      "source": "cache",
      "cheapness": 0.867,
      "factors": {
        "value_score": 1.0,
        "comps_percentile": 0.8
      },
      "intrinsic_value": null,
      "market_price": 1.42,
      "margin_of_safety": null,
      "peer_pct": {
        "pe": null,
        "ev_ebitda": null,
        "ev_rev": 0.2
      },
      "confidence": "medium",
      "notes": [
        "dcf-skipped: latest FCF not positive (lite DCF can't price money-losers)"
      ],
      "assumptions": {
        "horizon_yrs": 5,
        "terminal_g": 0.025,
        "erp": 0.05,
        "tax_rate": 0.21,
        "equity_weight": 0.7
      },
      "my_metrics": {
        "pe": null,
        "ev_ebitda": -11.2,
        "ev_rev": 0.72
      }
    },
    "WAST": {
      "ticker": "WAST",
      "computed_at": 1782168354.1521168,
      "source": "cache",
      "cheapness": null,
      "factors": {},
      "intrinsic_value": null,
      "market_price": 0.0378,
      "margin_of_safety": null,
      "peer_pct": {
        "pe": null,
        "ev_ebitda": null,
        "ev_rev": null
      },
      "confidence": "low",
      "notes": [
        "dcf-skipped: latest FCF not positive (lite DCF can't price money-losers)"
      ],
      "assumptions": {
        "horizon_yrs": 5,
        "terminal_g": 0.025,
        "erp": 0.05,
        "tax_rate": 0.21,
        "equity_weight": 0.7
      },
      "my_metrics": {
        "pe": null,
        "ev_ebitda": null,
        "ev_rev": 20.38
      }
    },
    "INTR": {
      "ticker": "INTR",
      "computed_at": 1782168365.0918722,
      "source": "cache",
      "cheapness": 1.0,
      "factors": {
        "value_score": 1.0,
        "comps_percentile": 1.0
      },
      "intrinsic_value": null,
      "market_price": 5.39,
      "margin_of_safety": null,
      "peer_pct": {
        "pe": 0.0,
        "ev_ebitda": null,
        "ev_rev": 0.0
      },
      "confidence": "medium",
      "notes": [
        "dcf-unreliable: |margin|=+8702% implausible (likely small/illiquid/cyclical FCF) \u2192 intrinsic suppressed & factor dropped; name leans on value_score"
      ],
      "assumptions": {
        "horizon_yrs": 5,
        "terminal_g": 0.025,
        "erp": 0.05,
        "tax_rate": 0.21,
        "equity_weight": 0.7
      },
      "my_metrics": {
        "pe": 8.56,
        "ev_ebitda": null,
        "ev_rev": 2.45
      }
    },
    "ACN": {
      "ticker": "ACN",
      "computed_at": 1782168359.530247,
      "source": "cache",
      "cheapness": 0.93,
      "factors": {
        "value_score": 0.901,
        "comps_percentile": 0.944
      },
      "intrinsic_value": null,
      "market_price": 124.83,
      "margin_of_safety": null,
      "peer_pct": {
        "pe": 0.167,
        "ev_ebitda": 0.0,
        "ev_rev": 0.0
      },
      "confidence": "medium",
      "notes": [
        "dcf-unreliable: |margin|=+180% implausible (likely small/illiquid/cyclical FCF) \u2192 intrinsic suppressed & factor dropped; name leans on value_score"
      ],
      "assumptions": {
        "horizon_yrs": 5,
        "terminal_g": 0.025,
        "erp": 0.05,
        "tax_rate": 0.21,
        "equity_weight": 0.7
      },
      "my_metrics": {
        "pe": 9.97,
        "ev_ebitda": 6.04,
        "ev_rev": 1.07
      }
    },
    "NTIP": {
      "ticker": "NTIP",
      "computed_at": 1782168377.2138348,
      "source": "cache",
      "cheapness": 1.0,
      "factors": {
        "value_score": 1.0,
        "comps_percentile": 1.0
      },
      "intrinsic_value": null,
      "market_price": 1.48,
      "margin_of_safety": null,
      "peer_pct": {
        "pe": null,
        "ev_ebitda": 0.0,
        "ev_rev": null
      },
      "confidence": "medium",
      "notes": [
        "dcf-skipped: latest FCF not positive (lite DCF can't price money-losers)"
      ],
      "assumptions": {
        "horizon_yrs": 5,
        "terminal_g": 0.025,
        "erp": 0.05,
        "tax_rate": 0.21,
        "equity_weight": 0.7
      },
      "my_metrics": {
        "pe": null,
        "ev_ebitda": 0.25,
        "ev_rev": null
      }
    },
    "NOC": {
      "ticker": "NOC",
      "computed_at": 1782168348.213873,
      "source": "cache",
      "cheapness": 0.707,
      "factors": {
        "value_score": 0.677,
        "comps_percentile": 0.889,
        "dcf_margin": 0.54
      },
      "intrinsic_value": 527.39,
      "market_price": 507.33,
      "margin_of_safety": 0.04,
      "peer_pct": {
        "pe": 0.0,
        "ev_ebitda": 0.0,
        "ev_rev": 0.333
      },
      "confidence": "high",
      "notes": [
        "dcf-beta: raw beta=-0.121 out of [0.7,2.5] \u2192 clamped/defaulted",
        "dcf: wacc=7.15%, g0=12.00%\u2192termg, terminal_g=2.50%, beta=0.70, net_debt=$15.5B"
      ],
      "assumptions": {
        "horizon_yrs": 5,
        "terminal_g": 0.025,
        "erp": 0.05,
        "tax_rate": 0.21,
        "equity_weight": 0.7
      },
      "my_metrics": {
        "pe": 15.89,
        "ev_ebitda": 12.26,
        "ev_rev": 2.11
      }
    },
    "SAIC": {
      "ticker": "SAIC",
      "computed_at": 1782168355.9248877,
      "source": "cache",
      "cheapness": 0.721,
      "factors": {
        "value_score": 0.829,
        "comps_percentile": 0.667
      },
      "intrinsic_value": null,
      "market_price": 100.6,
      "margin_of_safety": null,
      "peer_pct": {
        "pe": 0.0,
        "ev_ebitda": 0.4,
        "ev_rev": 0.6
      },
      "confidence": "medium",
      "notes": [
        "dcf-beta: raw beta=0.293 out of [0.7,2.5] \u2192 clamped/defaulted",
        "dcf-unreliable: |margin|=+176% implausible (likely small/illiquid/cyclical FCF) \u2192 intrinsic suppressed & factor dropped; name leans on value_score"
      ],
      "assumptions": {
        "horizon_yrs": 5,
        "terminal_g": 0.025,
        "erp": 0.05,
        "tax_rate": 0.21,
        "equity_weight": 0.7
      },
      "my_metrics": {
        "pe": 11.32,
        "ev_ebitda": 9.36,
        "ev_rev": 0.95
      }
    },
    "LDOS": {
      "ticker": "LDOS",
      "computed_at": 1782168367.0868247,
      "source": "cache",
      "cheapness": 0.699,
      "factors": {
        "value_score": 0.874,
        "comps_percentile": 0.611
      },
      "intrinsic_value": null,
      "market_price": 104.84,
      "margin_of_safety": null,
      "peer_pct": {
        "pe": 0.167,
        "ev_ebitda": 0.5,
        "ev_rev": 0.5
      },
      "confidence": "medium",
      "notes": [
        "dcf-beta: raw beta=0.515 out of [0.7,2.5] \u2192 clamped/defaulted",
        "dcf-unreliable: |margin|=+188% implausible (likely small/illiquid/cyclical FCF) \u2192 intrinsic suppressed & factor dropped; name leans on value_score"
      ],
      "assumptions": {
        "horizon_yrs": 5,
        "terminal_g": 0.025,
        "erp": 0.05,
        "tax_rate": 0.21,
        "equity_weight": 0.7
      },
      "my_metrics": {
        "pe": 9.59,
        "ev_ebitda": 8.32,
        "ev_rev": 1.16
      }
    },
    "LHX": {
      "ticker": "LHX",
      "computed_at": 1782168357.9680333,
      "source": "cache",
      "cheapness": 0.571,
      "factors": {
        "value_score": 0.456,
        "comps_percentile": 0.5,
        "dcf_margin": 0.7
      },
      "intrinsic_value": 343.04,
      "market_price": 285.83,
      "margin_of_safety": 0.2,
      "peer_pct": {
        "pe": 0.333,
        "ev_ebitda": 0.667,
        "ev_rev": 0.5
      },
      "confidence": "high",
      "notes": [
        "dcf: wacc=7.31%, g0=12.00%\u2192termg, terminal_g=2.50%, beta=0.75, net_debt=$6.9B"
      ],
      "assumptions": {
        "horizon_yrs": 5,
        "terminal_g": 0.025,
        "erp": 0.05,
        "tax_rate": 0.21,
        "equity_weight": 0.7
      },
      "my_metrics": {
        "pe": 31.07,
        "ev_ebitda": 33.67,
        "ev_rev": 5.62
      }
    },
    "LMT": {
      "ticker": "LMT",
      "computed_at": 1782168374.35044,
      "source": "cache",
      "cheapness": 0.668,
      "factors": {
        "value_score": 0.277,
        "comps_percentile": 0.756,
        "dcf_margin": 0.776
      },
      "intrinsic_value": 629.82,
      "market_price": 493.6,
      "margin_of_safety": 0.276,
      "peer_pct": {
        "pe": 0.333,
        "ev_ebitda": 0.4,
        "ev_rev": 0.0
      },
      "confidence": "high",
      "notes": [
        "dcf-beta: raw beta=0.106 out of [0.7,2.5] \u2192 clamped/defaulted",
        "dcf: wacc=7.15%, g0=5.71%\u2192termg, terminal_g=2.50%, beta=0.70, net_debt=$18.8B"
      ],
      "assumptions": {
        "horizon_yrs": 5,
        "terminal_g": 0.025,
        "erp": 0.05,
        "tax_rate": 0.21,
        "equity_weight": 0.7
      },
      "my_metrics": {
        "pe": 23.91,
        "ev_ebitda": 17.09,
        "ev_rev": 1.82
      }
    },
    "DDC": {
      "ticker": "DDC",
      "computed_at": 1782168370.1569123,
      "source": "cache",
      "cheapness": 0.555,
      "factors": {
        "value_score": 1.0,
        "comps_percentile": 0.333
      },
      "intrinsic_value": null,
      "market_price": 0.9731,
      "margin_of_safety": null,
      "peer_pct": {
        "pe": null,
        "ev_ebitda": null,
        "ev_rev": 0.667
      },
      "confidence": "medium",
      "notes": [
        "dcf-skipped: latest FCF not positive (lite DCF can't price money-losers)"
      ],
      "assumptions": {
        "horizon_yrs": 5,
        "terminal_g": 0.025,
        "erp": 0.05,
        "tax_rate": 0.21,
        "equity_weight": 0.7
      },
      "my_metrics": {
        "pe": null,
        "ev_ebitda": -3.59,
        "ev_rev": 2.92
      }
    },
    "BA": {
      "ticker": "BA",
      "computed_at": 1782168344.4886022,
      "source": "cache",
      "cheapness": 0.222,
      "factors": {
        "value_score": 0.0,
        "comps_percentile": 0.333
      },
      "intrinsic_value": null,
      "market_price": 220.83,
      "margin_of_safety": null,
      "peer_pct": {
        "pe": 1.0,
        "ev_ebitda": null,
        "ev_rev": 0.333
      },
      "confidence": "medium",
      "notes": [
        "dcf-skipped: latest FCF not positive (lite DCF can't price money-losers)"
      ],
      "assumptions": {
        "horizon_yrs": 5,
        "terminal_g": 0.025,
        "erp": 0.05,
        "tax_rate": 0.21,
        "equity_weight": 0.7
      },
      "my_metrics": {
        "pe": 86.94,
        "ev_ebitda": -62.91,
        "ev_rev": 2.22
      }
    },
    "SFDL": {
      "ticker": "SFDL",
      "computed_at": 1782168375.3154786,
      "source": "cache",
      "cheapness": 0.555,
      "factors": {
        "value_score": 1.0,
        "comps_percentile": 0.333
      },
      "intrinsic_value": null,
      "market_price": 37.8,
      "margin_of_safety": null,
      "peer_pct": {
        "pe": 0.833,
        "ev_ebitda": null,
        "ev_rev": 0.5
      },
      "confidence": "medium",
      "notes": [
        "dcf-beta: raw beta=0.426 out of [0.7,2.5] \u2192 clamped/defaulted",
        "dcf-unreliable: |margin|=+170% implausible (likely small/illiquid/cyclical FCF) \u2192 intrinsic suppressed & factor dropped; name leans on value_score"
      ],
      "assumptions": {
        "horizon_yrs": 5,
        "terminal_g": 0.025,
        "erp": 0.05,
        "tax_rate": 0.21,
        "equity_weight": 0.7
      },
      "my_metrics": {
        "pe": 9.95,
        "ev_ebitda": null,
        "ev_rev": 2.08
      }
    },
    "CRH": {
      "ticker": "CRH",
      "computed_at": 1782168362.9238646,
      "source": "cache",
      "cheapness": 0.465,
      "factors": {
        "value_score": 0.669,
        "comps_percentile": 0.778,
        "dcf_margin": 0.05
      },
      "intrinsic_value": 61.17,
      "market_price": 111.25,
      "margin_of_safety": -0.45,
      "peer_pct": {
        "pe": 0.167,
        "ev_ebitda": 0.5,
        "ev_rev": 0.0
      },
      "confidence": "high",
      "notes": [
        "dcf: wacc=8.85%, g0=12.00%\u2192termg, terminal_g=2.50%, beta=1.19, net_debt=$17.2B"
      ],
      "assumptions": {
        "horizon_yrs": 5,
        "terminal_g": 0.025,
        "erp": 0.05,
        "tax_rate": 0.21,
        "equity_weight": 0.7
      },
      "my_metrics": {
        "pe": 20.6,
        "ev_ebitda": 12.26,
        "ev_rev": 2.44
      }
    },
    "CACI": {
      "ticker": "CACI",
      "computed_at": 1782168360.975883,
      "source": "cache",
      "cheapness": 0.421,
      "factors": {
        "value_score": 0.819,
        "comps_percentile": 0.644,
        "dcf_margin": 0.0
      },
      "intrinsic_value": 181.52,
      "market_price": 449.72,
      "margin_of_safety": -0.596,
      "peer_pct": {
        "pe": 0.5,
        "ev_ebitda": 0.4,
        "ev_rev": 0.167
      },
      "confidence": "high",
      "notes": [
        "dcf-beta: raw beta=0.523 out of [0.7,2.5] \u2192 clamped/defaulted",
        "dcf: wacc=7.15%, g0=-2.32%\u2192termg, terminal_g=2.50%, beta=0.70, net_debt=$5.5B"
      ],
      "assumptions": {
        "horizon_yrs": 5,
        "terminal_g": 0.025,
        "erp": 0.05,
        "tax_rate": 0.21,
        "equity_weight": 0.7
      },
      "my_metrics": {
        "pe": 18.58,
        "ev_ebitda": 14.25,
        "ev_rev": 1.72
      }
    },
    "EML": {
      "ticker": "EML",
      "computed_at": 1782168349.4964168,
      "source": "cache",
      "cheapness": 0.321,
      "factors": {
        "value_score": 0.63,
        "comps_percentile": 0.467,
        "dcf_margin": 0.02
      },
      "intrinsic_value": 12.07,
      "market_price": 23.24,
      "margin_of_safety": -0.481,
      "peer_pct": {
        "pe": 1.0,
        "ev_ebitda": 0.4,
        "ev_rev": 0.2
      },
      "confidence": "high",
      "notes": [
        "dcf: wacc=7.74%, g0=12.00%\u2192termg, terminal_g=2.50%, beta=0.87, net_debt=$0.0B"
      ],
      "assumptions": {
        "horizon_yrs": 5,
        "terminal_g": 0.025,
        "erp": 0.05,
        "tax_rate": 0.21,
        "equity_weight": 0.7
      },
      "my_metrics": {
        "pe": 29.79,
        "ev_ebitda": 10.41,
        "ev_rev": 0.77
      }
    },
    "IBM": {
      "ticker": "IBM",
      "computed_at": 1782168368.8082323,
      "source": "cache",
      "cheapness": 0.383,
      "factors": {
        "value_score": 0.317,
        "comps_percentile": 0.222,
        "dcf_margin": 0.576
      },
      "intrinsic_value": 271.4,
      "market_price": 252.22,
      "margin_of_safety": 0.076,
      "peer_pct": {
        "pe": 0.833,
        "ev_ebitda": 0.667,
        "ev_rev": 0.833
      },
      "confidence": "high",
      "notes": [
        "dcf-beta: raw beta=0.665 out of [0.7,2.5] \u2192 clamped/defaulted",
        "dcf: wacc=7.15%, g0=12.00%\u2192termg, terminal_g=2.50%, beta=0.70, net_debt=$58.0B"
      ],
      "assumptions": {
        "horizon_yrs": 5,
        "terminal_g": 0.025,
        "erp": 0.05,
        "tax_rate": 0.21,
        "equity_weight": 0.7
      },
      "my_metrics": {
        "pe": 22.3,
        "ev_ebitda": 17.59,
        "ev_rev": 4.24
      }
    },
    "GFL": {
      "ticker": "GFL",
      "computed_at": 1782168351.4005911,
      "source": "cache",
      "cheapness": 0.261,
      "factors": {
        "value_score": 0.395,
        "comps_percentile": 0.456,
        "dcf_margin": 0.0
      },
      "intrinsic_value": -15.01,
      "market_price": 35.0,
      "margin_of_safety": -1.429,
      "peer_pct": {
        "pe": 0.8,
        "ev_ebitda": 0.167,
        "ev_rev": 0.667
      },
      "confidence": "high",
      "notes": [
        "dcf-beta: raw beta=0.5 out of [0.7,2.5] \u2192 clamped/defaulted",
        "dcf: wacc=7.15%, g0=-5.00%\u2192termg, terminal_g=2.50%, beta=0.70, net_debt=$8.5B"
      ],
      "assumptions": {
        "horizon_yrs": 5,
        "terminal_g": 0.025,
        "erp": 0.05,
        "tax_rate": 0.21,
        "equity_weight": 0.7
      },
      "my_metrics": {
        "pe": 94.59,
        "ev_ebitda": 12.8,
        "ev_rev": 3.17
      }
    },
    "ICUI": {
      "ticker": "ICUI",
      "computed_at": 1782168381.2074814,
      "source": "cache",
      "cheapness": 0.298,
      "factors": {
        "value_score": 0.488,
        "comps_percentile": 0.5,
        "dcf_margin": 0.0
      },
      "intrinsic_value": 43.47,
      "market_price": 136.14,
      "margin_of_safety": -0.681,
      "peer_pct": {
        "pe": 1.0,
        "ev_ebitda": 0.5,
        "ev_rev": 0.0
      },
      "confidence": "high",
      "notes": [
        "dcf: wacc=7.42%, g0=12.00%\u2192termg, terminal_g=2.50%, beta=0.78, net_debt=$1.1B"
      ],
      "assumptions": {
        "horizon_yrs": 5,
        "terminal_g": 0.025,
        "erp": 0.05,
        "tax_rate": 0.21,
        "equity_weight": 0.7
      },
      "my_metrics": {
        "pe": 73.59,
        "ev_ebitda": 14.64,
        "ev_rev": 2.11
      }
    },
    "LRCX": {
      "ticker": "LRCX",
      "computed_at": 1782168346.4328692,
      "source": "cache",
      "cheapness": 0.093,
      "factors": {
        "value_score": 0.0,
        "comps_percentile": 0.233,
        "dcf_margin": 0.0
      },
      "intrinsic_value": 63.33,
      "market_price": 409.54,
      "margin_of_safety": -0.845,
      "peer_pct": {
        "pe": 0.8,
        "ev_ebitda": 0.833,
        "ev_rev": 0.667
      },
      "confidence": "high",
      "notes": [
        "dcf: wacc=11.24%, g0=12.00%\u2192termg, terminal_g=2.50%, beta=1.87, net_debt=$-1.0B"
      ],
      "assumptions": {
        "horizon_yrs": 5,
        "terminal_g": 0.025,
        "erp": 0.05,
        "tax_rate": 0.21,
        "equity_weight": 0.7
      },
      "my_metrics": {
        "pe": 77.42,
        "ev_ebitda": 61.87,
        "ev_rev": 22.39
      }
    },
    "ROAD": {
      "ticker": "ROAD",
      "computed_at": 1782168372.2335906,
      "source": "cache",
      "cheapness": 0.133,
      "factors": {
        "value_score": 0.0,
        "comps_percentile": 0.333,
        "dcf_margin": 0.0
      },
      "intrinsic_value": 39.68,
      "market_price": 127.05,
      "margin_of_safety": -0.688,
      "peer_pct": {
        "pe": 0.8,
        "ev_ebitda": 0.6,
        "ev_rev": 0.6
      },
      "confidence": "high",
      "notes": [
        "dcf: wacc=7.80%, g0=12.00%\u2192termg, terminal_g=2.50%, beta=0.89, net_debt=$1.8B"
      ],
      "assumptions": {
        "horizon_yrs": 5,
        "terminal_g": 0.025,
        "erp": 0.05,
        "tax_rate": 0.21,
        "equity_weight": 0.7
      },
      "my_metrics": {
        "pe": 55.72,
        "ev_ebitda": 18.2,
        "ev_rev": 2.67
      }
    },
    "MDA": {
      "ticker": "MDA",
      "computed_at": 1782168353.32304,
      "source": "cache",
      "cheapness": 0.033,
      "factors": {
        "value_score": 0.099,
        "dcf_margin": 0.0
      },
      "intrinsic_value": 14.33,
      "market_price": 39.39,
      "margin_of_safety": -0.636,
      "peer_pct": {},
      "confidence": "medium",
      "notes": [
        "dcf-beta: raw beta=None out of [0.7,2.5] \u2192 clamped/defaulted",
        "dcf: wacc=8.20%, g0=-5.00%\u2192termg, terminal_g=2.50%, beta=1.00, net_debt=$0.0B"
      ],
      "assumptions": {
        "horizon_yrs": 5,
        "terminal_g": 0.025,
        "erp": 0.05,
        "tax_rate": 0.21,
        "equity_weight": 0.7
      },
      "my_metrics": {
        "pe": 69.11,
        "ev_ebitda": null,
        "ev_rev": null
      }
    },
    "ATEN": {
      "ticker": "ATEN",
      "computed_at": 1782168379.3128781,
      "source": "cache",
      "cheapness": 0.117,
      "factors": {
        "value_score": 0.0,
        "comps_percentile": 0.2,
        "dcf_margin": 0.092
      },
      "intrinsic_value": 19.98,
      "market_price": 33.77,
      "margin_of_safety": -0.408,
      "peer_pct": {
        "pe": 0.6,
        "ev_ebitda": 0.8,
        "ev_rev": 1.0
      },
      "confidence": "high",
      "notes": [
        "dcf: wacc=8.83%, g0=12.00%\u2192termg, terminal_g=2.50%, beta=1.18, net_debt=$-0.1B"
      ],
      "assumptions": {
        "horizon_yrs": 5,
        "terminal_g": 0.025,
        "erp": 0.05,
        "tax_rate": 0.21,
        "equity_weight": 0.7
      },
      "my_metrics": {
        "pe": 55.36,
        "ev_ebitda": 33.66,
        "ev_rev": 7.52
      }
    }
  },
  "reports": {
    "BZFD": "reports/BZFD_research.xlsx",
    "WAST": "reports/WAST_research.xlsx",
    "INTR": "reports/INTR_research.xlsx",
    "ACN": "reports/ACN_research.xlsx",
    "NTIP": "reports/NTIP_research.xlsx"
  }
}